{"cameraMode":{"drawMode":0,"name":"Shaded","section":"Shading Mode"},"sceneLighting":true,"audioPlay":false,"sceneViewState":{"m_AlwaysRefresh":false,"showFog":true,"showSkybox":true,"showFlares":true,"showImageEffects":true,"showParticleSystems":true,"showVisualEffectGraphs":true,"m_FxEnabled":true},"in2DMode":false,"pivot":{"x":4.1971893310546879,"y":4.0198974609375,"z":-4.755836486816406},"rotation":{"x":0.09183520078659058,"y":-0.14975965023040772,"z":-0.01387001108378172,"w":-0.9844664931297302},"size":3.971608877182007,"orthographic":false}